LICENSE
README.md
setup.py
brazilian_data/__init__.py
brazilian_data/economic_data.py
brazilian_data/economic_data_async.py
brazilian_data/economic_data_collection.py
brazilian_data/economic_data_collection_async.py
brazilian_data/economic_data_process.py
brazilian_data/economic_data_process_async.py
brazilian_data.egg-info/PKG-INFO
brazilian_data.egg-info/SOURCES.txt
brazilian_data.egg-info/dependency_links.txt
brazilian_data.egg-info/requires.txt
brazilian_data.egg-info/top_level.txt
brazilian_data/configuracao_apis/__init__.py
brazilian_data/configuracao_apis/api_fred.py
brazilian_data/configuracao_apis/api_quandl.py
tests/__init__.py
tests/test_economi_data_async.py
tests/test_economic_data.py
tests/test_economic_data_process.py