Metadata-Version: 2.1
Name: brazilian-data
Version: 0.1.2
Summary: This repository is part of the creation of a package for collecting Brazilian data
Author: Jeferson Sehnem
Author-email: sehnemjeferson@gmail.com
License: MIT License
Keywords: Brazilian Data
Requires-Python: >=3.10
License-File: LICENSE
